metatable/__init__.py
metatable/metatable.py
metatable-1.3.0.dist-info/LICENSE
metatable-1.3.0.dist-info/METADATA
metatable-1.3.0.dist-info/WHEEL
metatable-1.3.0.dist-info/top_level.txt
metatable-1.3.0.dist-info/RECORD
