Metadata-Version: 2.1
Name: metatable
Version: 1.3.0
Summary: Extensible table data structure that supports concise workflow descriptions via user-defined combinators.
Author: Andrei Lapets
Author-email: a@lapets.io
License: MIT
Project-URL: Repository, https://github.com/reity/metatable
Project-URL: Documentation, https://metatable.readthedocs.io
Requires-Python: >=3.7
License-File: LICENSE
Requires-Dist: symbolism (~=0.4)
Provides-Extra: coveralls
Requires-Dist: coveralls (~=3.3.1) ; extra == 'coveralls'
Provides-Extra: docs
Requires-Dist: toml (~=0.10.2) ; extra == 'docs'
Requires-Dist: sphinx (~=4.2.0) ; extra == 'docs'
Requires-Dist: sphinx-rtd-theme (~=1.0.0) ; extra == 'docs'
Requires-Dist: sphinx-autodoc-typehints (~=1.12.0) ; extra == 'docs'
Provides-Extra: lint
Requires-Dist: pylint (~=2.14.0) ; extra == 'lint'
Provides-Extra: publish
Requires-Dist: build (~=0.8) ; extra == 'publish'
Requires-Dist: twine (~=4.0) ; extra == 'publish'
Provides-Extra: test
Requires-Dist: pytest (~=7.0) ; extra == 'test'
Requires-Dist: pytest-cov (~=3.0) ; extra == 'test'
